{"type":"PR","pr":{"number":557,"head":"571f9d94623fba8b8645e4b261194fe5ffc45f2a"},"user":"SENDatGitHub","status":"pending_publish","branch":"cms/reflecta-network_2018-12-05","collection":"members","title":"Reflecta.Network","description":"Das Reflecta.Network ist eine digitale Plattform für diejenigen, die Antworten auf die drängenden Fragen unserer Zeit suchen. Das Ziel ist es, die UN Global Goals, deren Akteure und ihren Social Impact sichtbar zu machen. Changemaker, Unternehmen und Organisationen können durch einen intelligenten Algorithmus zusammengebracht werden. Projekte, die einen gesellschaftlichen Mehrwert bieten, werden möglich gemacht, gefördert und professionalisiert.","objects":{"entry":{"path":"src/members/reflecta-network_2018-12-05.md","sha":"cf9c35d7e81bafd3b674acaeda44f7159cadee61"},"files":[]},"timeStamp":"2019-02-05T10:17:56.886Z"}