{"type":"PR","pr":{"number":1001,"head":"2dd52eb0631ef547427e9c81985fb6abe7533346"},"user":"SEND-Merlind","status":"draft","branch":"cms/schoepflin-stiftung","collection":"partner","title":"Schöpflin Stiftung","description":"_\"SEND setzt sich als Lobby- und Netzwerkorganisation dafür ein, die Rahmenbedingungen für Sozialunternehmen zu verbessern und ihnen eine lautere Stimme zu geben. Wir fördern SEND e.V., weil das Netzwerk damit Wegbereiter für verantwortungsvolles Unternehmertum in Deutschland ist. Jetzt und für die Zukunft der jungen und kommenden Generationen.\"_\n\nLukas Harlan","objects":{"entry":{"path":"src/partners/schoepflin-stiftung.md","sha":"8c06a813a19a23e1edffdf373360953eda3e089c"},"files":[]},"timeStamp":"2019-11-27T17:09:18.747Z"}