{"type":"PR","pr":{"number":810,"head":"b1cc691ddfc18d56ee4e35e06fdd6073b03cbcab"},"user":"SENDatGitHub","status":"draft","branch":"cms/studio2b_2019-09-09","collection":"members","title":"Studio2B","description":"Als Berliner Sozialunternehmen entwickelt die Studio2B GmbH seit 2012 innovative Konzepte für die digitale Berufsbildung und Berufsorientierung. Mit unseren Angeboten veedu, SchulePLUS und Dein erster Tag erreichen wir Schüler*innen, Azubis, Berufstätige und Arbeitssuchende in ganz Deutschland und Österreich. Wir produzieren E-Learning-Kurse, führen Präsenzworkshops an Schulen durch und erstellen 360-Grad-Erkundungen von zahlreichen Ausbildungsberufen und Dualen Studiengängen. Bei unserer Arbeit werden wir von der Kultusministerkonferenz und dem weltweit größten Netzwerk für Sozialunternehmer*innen, Ashoka, unterstützt. Eine Vielzahl unserer Projekte wird außerdem vom Europäischen Sozialfond, dem Land Berlin, der Bundesrepublik Deutschland oder der Berliner Wirtschaft gefördert.","objects":{"entry":{"path":"src/members/studio2b_2019-09-09.md","sha":"8a154d971953f51a97e32d747adfe42ae98ca732"},"files":[{"path":"/static/uploads/studio2b.png","sha":"db32a131f685a530d1449b9be76f97ba9b223939"}]},"timeStamp":"2019-09-09T15:14:54.622Z"}