{"type":"PR","pr":{"number":967,"head":"d3db8eeea5b4056ea22233454e5b9c40af210843"},"user":"SENDatGitHub","status":"pending_publish","branch":"cms/voltastics-_2019-09-19","collection":"members","title":"#VOLTASTICS ","description":"#VOLTASTICS - Mehr Sichtbarkeit und Anerkennung für ehrenamtliches und freiwilliges Engagement in Deutschland.\n\nÜber 30 Millionen freiwillig Engagierte leisten einen wertvollen Beitrag für unsere Gesellschaft. Wir begeistern Freiwillige Organisationen Unternehmen und Städte sich digital zu vernetzen um freiwilliges Engagement sichtbarer zu machen und gegenseitige Unterstützung besser zu organisieren.\n\nWir vernetzen die Player des ehrenamtlichen und freiwilligen Engagements in Deutschland. Freiwillig Engagierte bei #VOLTASTICS erfassen Ihre Aktivitäten. Automatisch via App. Unternehmen Organisationen und Städte können Freiwillige somit aktiver unterstützen.","objects":{"entry":{"path":"src/members/voltastics-_2019-09-19.md","sha":"c059f9edf3620b549326749e39aed391a4e7683b"},"files":[{"path":"/static/uploads/voltastics.png","sha":"3f8bfa2968057cb861f14fb7326ab45381bf42d5"},{"path":"/static/uploads/voltastics.png","sha":"3f8bfa2968057cb861f14fb7326ab45381bf42d5"}]},"timeStamp":"2019-11-18T14:21:53.923Z"}